JiagouZhengjiZhidaoFix1/README.md
JiagouZhengjiZhidaoFix1/__init__.py
JiagouZhengjiZhidaoFix1/__main__.py
JiagouZhengjiZhidaoFix1/file.epub
JiagouZhengjiZhidaoFix1/index.html
JiagouZhengjiZhidaoFix1/css/__init__.py
JiagouZhengjiZhidaoFix1/css/annotations.css
JiagouZhengjiZhidaoFix1/css/main.css
JiagouZhengjiZhidaoFix1/css/normalize.css
JiagouZhengjiZhidaoFix1/css/popup.css
JiagouZhengjiZhidaoFix1/font/__init__.py
JiagouZhengjiZhidaoFix1/font/fontello.eot
JiagouZhengjiZhidaoFix1/font/fontello.svg
JiagouZhengjiZhidaoFix1/font/fontello.ttf
JiagouZhengjiZhidaoFix1/font/fontello.woff
JiagouZhengjiZhidaoFix1/img/__init__.py
JiagouZhengjiZhidaoFix1/img/annotator-glyph-sprite.png
JiagouZhengjiZhidaoFix1/img/annotator-icon-sprite.png
JiagouZhengjiZhidaoFix1/img/apple-touch-icon.png
JiagouZhengjiZhidaoFix1/img/cancelfullscreen.png
JiagouZhengjiZhidaoFix1/img/close.png
JiagouZhengjiZhidaoFix1/img/fullscreen.png
JiagouZhengjiZhidaoFix1/img/loader.gif
JiagouZhengjiZhidaoFix1/img/menu-icon.png
JiagouZhengjiZhidaoFix1/img/save.png
JiagouZhengjiZhidaoFix1/img/saved.png
JiagouZhengjiZhidaoFix1/img/settings-s.png
JiagouZhengjiZhidaoFix1/img/settings.png
JiagouZhengjiZhidaoFix1/img/star.png
JiagouZhengjiZhidaoFix1/js/__init__.py
JiagouZhengjiZhidaoFix1/js/epub.js
JiagouZhengjiZhidaoFix1/js/epub.min.js
JiagouZhengjiZhidaoFix1/js/epub.min.map
JiagouZhengjiZhidaoFix1/js/hooks.min.js
JiagouZhengjiZhidaoFix1/js/hooks.min.map
JiagouZhengjiZhidaoFix1/js/reader.js
JiagouZhengjiZhidaoFix1/js/reader.js.map
JiagouZhengjiZhidaoFix1/js/reader.min.js
JiagouZhengjiZhidaoFix1/js/reader.min.map
JiagouZhengjiZhidaoFix1/js/hooks/__init__.py
JiagouZhengjiZhidaoFix1/js/hooks/extensions/__init__.py
JiagouZhengjiZhidaoFix1/js/hooks/extensions/highlight.js
JiagouZhengjiZhidaoFix1/js/libs/__init__.py
JiagouZhengjiZhidaoFix1/js/libs/jquery.min.js
JiagouZhengjiZhidaoFix1/js/libs/localforage.min.js
JiagouZhengjiZhidaoFix1/js/libs/screenfull.js
JiagouZhengjiZhidaoFix1/js/libs/screenfull.min.js
jiagou_zhengji_zhidao_fix1-2025.3.24.0.dist-info/METADATA
jiagou_zhengji_zhidao_fix1-2025.3.24.0.dist-info/WHEEL
jiagou_zhengji_zhidao_fix1-2025.3.24.0.dist-info/entry_points.txt
jiagou_zhengji_zhidao_fix1-2025.3.24.0.dist-info/top_level.txt
jiagou_zhengji_zhidao_fix1-2025.3.24.0.dist-info/RECORD
